[{"affixAttr":{"36182&免费安装服务":"pop8010773448","36281增压款&有偿安装":"pop8010564770","36281经典款&有偿安装":"pop8010564769","36281超薄款&有偿安装":"pop8010564771","pagType":"1","skuId":"pop8010564769"},"brand":"九牧","brandCode":"17948","brandId":"71910310","buyWay":[],"bztType":1,"detailHref":"//item.gome.com.cn/A0006321120-pop8010564769.html","energyState":0,"gomePrice":669,"goodsColor":[],"goodsImgs":[{"href":"//item.gome.com.cn/bigimage/A0006321120-pop8010564769.html","imgOtherAttr":{},"linkOtherAttr":{},"src":"//gfs17.gomein.net.cn/T1paVyB4LT1RCvBVdK"},{"href":"//item.gome.com.cn/bigimage/A0006321120-pop8010564769.html","imgOtherAttr":{},"linkOtherAttr":{},"src":"//gfs2.gomein.net.cn/T1Vy_yBXET1RCvBVdK"},{"href":"//item.gome.com.cn/bigimage/A0006321120-pop8010564769.html","imgOtherAttr":{},"linkOtherAttr":{},"src":"//gfs3.gomein.net.cn/T1na_yBvWT1RCvBVdK"},{"href":"//item.gome.com.cn/bigimage/A0006321120-pop8010564769.html","imgOtherAttr":{},"linkOtherAttr":{},"src":"//gfs.gomein.net.cn/T1Ja_yBgZT1RCvBVdK"},{"href":"//item.gome.com.cn/bigimage/A0006321120-pop8010564769.html","imgOtherAttr":{},"linkOtherAttr":{},"src":"//gfs4.gomein.net.cn/T1LRbyB5_T1RCvBVdK"}],"htmlHref":"//desc.gome.com.cn/html/bbchtml/productDesc/descHtml201710/desc04/A0006321120.html","name":"JOMOO九牧 可升降淋浴花洒 空气能出水升级经典增压超薄淋浴器 莲蓬头花洒 36281(36281经典款)","operADHref":"//desc.gome.com.cn/advert/platformad/cat21445652/top.html","price":0,"productId":"A0006321120","productType":"product","programId":"111111111","salesProperty":[{"booleanMainsale":"true","booleanPic":"true","chinesename":"颜色","hidden":"false","salesNameNo":"8ac55c9d2cf8","skutions":[{"alt":"36281经典款","id":"b076b15f3b77","imgOtherAttr":{},"linkOtherAttr":{},"src":"//gfs17.gomein.net.cn/T1paVyB4LT1RCvBVdK","target":"cur","title":"36281经典款","weight":"1"},{"alt":"36281增压款","id":"82764bebe350","imgOtherAttr":{},"linkOtherAttr":{},"src":"//gfs17.gomein.net.cn/T1WrYbB7Jv1RCvBVdK","title":"36281增压款","weight":"2"},{"alt":"36281超薄款","id":"a7311b307d25","imgOtherAttr":{},"linkOtherAttr":{},"src":"//gfs17.gomein.net.cn/T1lhCgBCWv1RCvBVdK","title":"36281超薄款","weight":"3"},{"alt":"36182","id":"db853b999a00","imgOtherAttr":{},"linkOtherAttr":{},"src":"//gfs17.gomein.net.cn/T1RkL_BbYT1RCvBVdK","title":"36182","weight":"18"}]},{"booleanMainsale":"false","booleanPic":"false","chinesename":"服务","hidden":"false","salesNameNo":"dc3502ac8509","skutions":[{"alt":"免费安装服务","id":"ab10972c44c4","imgOtherAttr":{},"linkOtherAttr":{},"title":"免费安装服务","weight":"1"},{"alt":"有偿安装","id":"c4d99be8b9d9","imgOtherAttr":{},"linkOtherAttr":{},"target":"cur","title":"有偿安装","weight":"3"}]}],"sapSkuType":"ZBBC","selltype":"0","shelfCtgy":"PR01","shopFlag":"1","shopName":"九牧官方旗舰店","shopNo":"80014245","sku":"pop8010564769","skuBlackList":false,"skuId":"pop8010564769","skuNo":"8010564769","skuNoMap":{"pop8010564769":"8010564769","pop8010564770":"8010564770","pop8010564771":"8010564771","pop8010773448":"8010773448"},"skuType":"ZBBC","stats":1,"suitSku":[],"threeDflag":false,"vipShopFlag":"0"},{"affixAttr":{"pagType":"1","skuId":"pop8012772556","右角位&13米":"pop8012772556","右角位&15米":"pop8012772555","右角位&17米":"pop8012772554","左角位&13米":"pop8012772553","左角位&15米":"pop8012772552","左角位&17米":"pop8012772551","默认&13米":"pop8010916853","默认&15米":"pop8010478695","默认&17米":"pop8010916852"},"brand":"科勒","brandCode":"18898","brandId":"17808262","buyWay":[],"bztType":1,"detailHref":"//item.gome.com.cn/A0006307312-pop8012772556.html","energyState":0,"gomePrice":6699,"goodsColor":[],"goodsImgs":[{"href":"//item.gome.com.cn/bigimage/A0006307312-pop8012772556.html","imgOtherAttr":{},"linkOtherAttr":{},"src":"//gfs17.gomein.net.cn/T1ncJbBQZv1RCvBVdK"},{"href":"//item.gome.com.cn/bigimage/A0006307312-pop8012772556.html","imgOtherAttr":{},"linkOtherAttr":{},"src":"//gfs2.gomein.net.cn/T1vFVbBbKv1RCvBVdK"},{"href":"//item.gome.com.cn/bigimage/A0006307312-pop8012772556.html","imgOtherAttr":{},"linkOtherAttr":{},"src":"//gfs3.gomein.net.cn/T1febbBCCv1RCvBVdK"},{"href":"//item.gome.com.cn/bigimage/A0006307312-pop8012772556.html","imgOtherAttr":{},"linkOtherAttr":{},"src":"//gfs4.gomein.net.cn/T17nWQBb_v1RCvBVdK"},{"href":"//item.gome.com.cn/bigimage/A0006307312-pop8012772556.html","imgOtherAttr":{},"linkOtherAttr":{},"src":"//gfs1.gomein.net.cn/T1g1EbBybv1RCvBVdK"}],"htmlHref":"//desc.gome.com.cn/html/bbchtml/productDesc/descHtml201709/desc04/A0006307312.html","name":"科勒希尔维独立浴缸亚克力浴缸K-99023/99024/99017/99018/99013/99014(含裙边扶手排水)","operADHref":"//desc.gome.com.cn/advert/platformad/cat21445658/top.html","price":0,"productId":"A0006307312","productType":"product","programId":"111111111","salesProperty":[{"booleanMainsale":"true","booleanPic":"true","chinesename":"颜色","hidden":"false","salesNameNo":"8ac55c9d2cf8","skutions":[{"alt":"默认","id":"2409a24e864a","imgOtherAttr":{},"linkOtherAttr":{},"src":"//gfs17.gomein.net.cn/T1gUJTBmdv1RCvBVdK","title":"默认","weight":"1"},{"alt":"左角位","id":"e901f029c09a","imgOtherAttr":{},"linkOtherAttr":{},"src":"//gfs17.gomein.net.cn/T1ySEbB_ET1RCvBVdK","title":"左角位","weight":"5"},{"alt":"右角位","id":"85af01f48e5a","imgOtherAttr":{},"linkOtherAttr":{},"src":"//gfs17.gomein.net.cn/T1ncJbBQZv1RCvBVdK","target":"cur","title":"右角位","weight":"6"}]},{"booleanMainsale":"false","booleanPic":"false","chinesename":"版本","hidden":"false","salesNameNo":"c80c62c4448d","skutions":[{"alt":"17米","id":"45f54df0b02a","imgOtherAttr":{},"linkOtherAttr":{},"title":"1.7米","weight":"2"},{"alt":"15米","id":"f8d2662b0959","imgOtherAttr":{},"linkOtherAttr":{},"title":"1.5米","weight":"3"},{"alt":"13米","id":"ea3d59b6cd71","imgOtherAttr":{},"linkOtherAttr":{},"target":"cur","title":"1.3米","weight":"4"}]}],"sapSkuType":"ZBBC","selltype":"0","shelfCtgy":"PR01","shopFlag":"1","shopName":"科勒协佩居专卖店","shopNo":"80014571","sku":"pop8012772556","skuBlackList":false,"skuId":"pop8012772556","skuNo":"8012772556","skuNoMap":{"pop8010478695":"8010478695","pop8010916852":"8010916852","pop8010916853":"8010916853","pop8012772551":"8012772551","pop8012772552":"8012772552","pop8012772553":"8012772553","pop8012772554":"8012772554","pop8012772555":"8012772555","pop8012772556":"8012772556"},"skuType":"ZBBC","stats":1,"suitSku":[],"threeDflag":false,"vipShopFlag":"0"},{"affixAttr":{"300mm马桶喷枪花洒套装 含赠品":"pop8010218484","400mm马桶喷枪花洒套装 含赠品":"pop8010218485","pagType":"1","skuId":"pop8010218484"},"brand":"箭牌","brandCode":"03741","brandId":"71908895","buyWay":[],"bztType":1,"detailHref":"//item.gome.com.cn/A0006268708-pop8010218484.html","energyState":0,"gomePrice":1649,"goodsColor":[],"goodsImgs":[{"href":"//item.gome.com.cn/bigimage/A0006268708-pop8010218484.html","imgOtherAttr":{},"linkOtherAttr":{},"src":"//gfs17.gomein.net.cn/T1h6_yBgCT1RCvBVdK"},{"href":"//item.gome.com.cn/bigimage/A0006268708-pop8010218484.html","imgOtherAttr":{},"linkOtherAttr":{},"src":"//gfs4.gomein.net.cn/T1AUbyB7bT1RCvBVdK"},{"href":"//item.gome.com.cn/bigimage/A0006268708-pop8010218484.html","imgOtherAttr":{},"linkOtherAttr":{},"src":"//gfs1.gomein.net.cn/T1wcdyBvZv1RCvBVdK"},{"href":"//item.gome.com.cn/bigimage/A0006268708-pop8010218484.html","imgOtherAttr":{},"linkOtherAttr":{},"src":"//gfs1.gomein.net.cn/T1.chyBbCv1RCvBVdK"},{"href":"//item.gome.com.cn/bigimage/A0006268708-pop8010218484.html","imgOtherAttr":{},"linkOtherAttr":{},"src":"//gfs1.gomein.net.cn/T1x6_yB7AT1RCvBVdK"}],"htmlHref":"//desc.gome.com.cn/html/bbchtml/productDesc/descHtml201707/desc04/A0006268708.html","name":"箭牌花洒马桶套装","operADHref":"//desc.gome.com.cn/advert/platformad/cat10005537/top.html","price":0,"productId":"A0006268708","productType":"product","programId":"111111111","salesProperty":[{"booleanMainsale":"true","booleanPic":"true","chinesename":"颜色","hidden":"false","salesNameNo":"8ac55c9d2cf8","skutions":[{"alt":"300mm马桶喷枪花洒套装 含赠品","id":"4fbe248237d9","imgOtherAttr":{},"linkOtherAttr":{},"src":"//gfs17.gomein.net.cn/T1h6_yBgCT1RCvBVdK","target":"cur","title":"300mm马桶+喷枪花洒套装 含赠品","weight":"1"},{"alt":"400mm马桶喷枪花洒套装 含赠品","id":"e2bf68e7a1ae","imgOtherAttr":{},"linkOtherAttr":{},"src":"//gfs17.gomein.net.cn/T1ycxyBQJv1RCvBVdK","title":"400mm马桶+喷枪花洒套装 含赠品","weight":"3"}]}],"sapSkuType":"ZBBC","selltype":"0","shelfCtgy":"PR01","shopFlag":"1","shopName":"箭牌厨卫旗舰店","shopNo":"80013325","sku":"pop8010218484","skuBlackList":false,"skuId":"pop8010218484","skuNo":"8010218484","skuNoMap":{"pop8010218484":"8010218484","pop8010218485":"8010218485"},"skuType":"ZBBC","stats":1,"suitSku":[],"threeDflag":false,"vipShopFlag":"0"},{"affixAttr":{"pagType":"1","skuId":"pop8010875178","卡通狗橙25W三段调色 直径41cm":"pop8010875180","卡通狗蓝25W三段调色 直径41cm":"pop8010875179","悦牡丹25W 三段调色 直径40cm":"pop8010875176","方缘25W 三段调色 直径40cm":"pop8010875177","星稀25W 三段调色 直径38cm":"pop8010875174","映旋25W 三段调色 直径38cm":"pop8010875173","晶澈白25W 三段调色 直径41cm":"pop8010875165","晶澈蓝25W 三段调色 直径41cm":"pop8010875166","棱影25W 三段调色 直径39cm":"pop8010549942","沁花25W 三段调色 直径39cm":"pop8010875175","灵羽粉25W 三段调色 直径41cm":"pop8010875170","灵羽金25W 三段调色 直径41cm":"pop8010875169","童花橙25W 三段调色 直径45cm":"pop8010875183","童花粉25W 三段调色 直径45cm":"pop8010875182","绽放25W 三段调色 直径35cm":"pop8010875181","花语25W 三段调色 直径39cm":"pop8010875178","花韵紫25W 三段调色 直径41cm":"pop8010875167","花韵蓝25W 三段调色 直径41cm":"pop8010875168","雀翎白25W 三段调色 直径41cm":"pop8010875172","雀翎蓝25W 三段调色 直径41cm":"pop8010875171"},"brand":"FSL","brandCode":"06077","brandId":"97913008","buyWay":[],"bztType":1,"detailHref":"//item.gome.com.cn/A0006318726-pop8010875178.html","energyState":0,"gomePrice":125,"goodsColor":[],"goodsImgs":[{"href":"//item.gome.com.cn/bigimage/A0006318726-pop8010875178.html","imgOtherAttr":{},"linkOtherAttr":{},"src":"//gfs17.gomein.net.cn/T1yh_bB5LT1RCvBVdK"},{"href":"//item.gome.com.cn/bigimage/A0006318726-pop8010875178.html","imgOtherAttr":{},"linkOtherAttr":{},"src":"//gfs2.gomein.net.cn/T15nbQBQET1RCvBVdK"},{"href":"//item.gome.com.cn/bigimage/A0006318726-pop8010875178.html","imgOtherAttr":{},"linkOtherAttr":{},"src":"//gfs1.gomein.net.cn/T1xUx_BCWT1RCvBVdK"},{"href":"//item.gome.com.cn/bigimage/A0006318726-pop8010875178.html","imgOtherAttr":{},"linkOtherAttr":{},"src":"//gfs2.gomein.net.cn/T1gm_bB5xT1RCvBVdK"},{"href":"//item.gome.com.cn/bigimage/A0006318726-pop8010875178.html","imgOtherAttr":{},"linkOtherAttr":{},"src":"//gfs4.gomein.net.cn/T1tFKsB5hT1RCvBVdK"}],"htmlHref":"//desc.gome.com.cn/html/bbchtml/productDesc/descHtml201710/desc04/A0006318726.html","name":"FSL佛山照明 led卧室灯","operADHref":"//desc.gome.com.cn/advert/platformad/cat21445665/top.html","price":0,"productId":"A0006318726","productType":"product","programId":"111111111","salesProperty":[{"booleanMainsale":"true","booleanPic":"true","chinesename":"颜色","hidden":"false","salesNameNo":"8ac55c9d2cf8","skutions":[{"alt":"晶澈白25W 三段调色 直径41cm","id":"5f2252d79297","imgOtherAttr":{},"linkOtherAttr":{},"src":"//gfs17.gomein.net.cn/T16NKbBgAT1RCvBVdK","title":"晶澈白25W 三段调色 直径41cm","weight":"119"},{"alt":"晶澈蓝25W 三段调色 直径41cm","id":"dc5a1262a5e8","imgOtherAttr":{},"linkOtherAttr":{},"src":"//gfs17.gomein.net.cn/T1Tr_QB5ET1RCvBVdK","title":"晶澈蓝25W 三段调色 直径41cm","weight":"120"},{"alt":"花韵紫25W 三段调色 直径41cm","id":"b8aa36db4a6d","imgOtherAttr":{},"linkOtherAttr":{},"src":"//gfs17.gomein.net.cn/T1AlEjB__T1RCvBVdK","title":"花韵紫25W 三段调色 直径41cm","weight":"122"},{"alt":"花韵蓝25W 三段调色 直径41cm","id":"274fb5adfbf8","imgOtherAttr":{},"linkOtherAttr":{},"src":"//gfs17.gomein.net.cn/T19tYgBCxv1RCvBVdK","title":"花韵蓝25W 三段调色 直径41cm","weight":"123"},{"alt":"灵羽金25W 三段调色 直径41cm","id":"c668bfb9f06b","imgOtherAttr":{},"linkOtherAttr":{},"src":"//gfs17.gomein.net.cn/T1ElA_BshT1RCvBVdK","title":"灵羽金25W 三段调色 直径41cm","weight":"124"},{"alt":"灵羽粉25W 三段调色 直径41cm","id":"ed19b71e1234","imgOtherAttr":{},"linkOtherAttr":{},"src":"//gfs17.gomein.net.cn/T1PN_bBgAT1RCvBVdK","title":"灵羽粉25W 三段调色 直径41cm","weight":"125"},{"alt":"雀翎蓝25W 三段调色 直径41cm","id":"ce7a9f1da012","imgOtherAttr":{},"linkOtherAttr":{},"src":"//gfs17.gomein.net.cn/T1KGVgBgET1RCvBVdK","title":"雀翎蓝25W 三段调色 直径41cm","weight":"126"},{"alt":"雀翎白25W 三段调色 直径41cm","id":"5debc98039af","imgOtherAttr":{},"linkOtherAttr":{},"src":"//gfs17.gomein.net.cn/T16kJjBy_v1RCvBVdK","title":"雀翎白25W 三段调色 直径41cm","weight":"127"},{"alt":"映旋25W 三段调色 直径38cm","id":"92468bdecf52","imgOtherAttr":{},"linkOtherAttr":{},"src":"//gfs17.gomein.net.cn/T17QKQB5ET1RCvBVdK","title":"映旋25W 三段调色 直径38cm","weight":"156"},{"alt":"星稀25W 三段调色 直径38cm","id":"4251c825e9bb","imgOtherAttr":{},"linkOtherAttr":{},"src":"//gfs17.gomein.net.cn/T1mP__BgxT1RCvBVdK","title":"星稀25W 三段调色 直径38cm","weight":"157"},{"alt":"沁花25W 三段调色 直径39cm","id":"5ffbb644a679","imgOtherAttr":{},"linkOtherAttr":{},"src":"//gfs17.gomein.net.cn/T1saKgBCAv1RCvBVdK","title":"沁花25W 三段调色 直径39cm","weight":"158"},{"alt":"悦牡丹25W 三段调色 直径40cm","id":"624d70b5b9a4","imgOtherAttr":{},"linkOtherAttr":{},"src":"//gfs17.gomein.net.cn/T1lJxQBQLT1RCvBVdK","title":"悦牡丹25W 三段调色 直径40cm","weight":"159"},{"alt":"方缘25W 三段调色 直径40cm","id":"6951a16b7516","imgOtherAttr":{},"linkOtherAttr":{},"src":"//gfs17.gomein.net.cn/T1v1bbB5ET1RCvBVdK","title":"方缘25W 三段调色 直径40cm","weight":"160"},{"alt":"花语25W 三段调色 直径39cm","id":"05913f0e0903","imgOtherAttr":{},"linkOtherAttr":{},"src":"//gfs17.gomein.net.cn/T1yh_bB5LT1RCvBVdK","target":"cur","title":"花语25W 三段调色 直径39cm","weight":"161"},{"alt":"卡通狗蓝25W三段调色 直径41cm","id":"f8f7b9504ae2","imgOtherAttr":{},"linkOtherAttr":{},"src":"//gfs17.gomein.net.cn/T1RGD_BgxT1RCvBVdK","title":"卡通狗蓝25W三段调色 直径41cm","weight":"162"},{"alt":"卡通狗橙25W三段调色 直径41cm","id":"85d5578119af","imgOtherAttr":{},"linkOtherAttr":{},"src":"//gfs17.gomein.net.cn/T12kdjBCCv1RCvBVdK","title":"卡通狗橙25W三段调色 直径41cm","weight":"163"},{"alt":"绽放25W 三段调色 直径35cm","id":"48b1d29792e1","imgOtherAttr":{},"linkOtherAttr":{},"src":"//gfs17.gomein.net.cn/T1CzhjB4Zv1RCvBVdK","title":"绽放25W 三段调色 直径35cm","weight":"164"},{"alt":"童花粉25W 三段调色 直径45cm","id":"e12a32e8dc60","imgOtherAttr":{},"linkOtherAttr":{},"src":"//gfs17.gomein.net.cn/T1q8JbBgAT1RCvBVdK","title":"童花粉25W 三段调色 直径45cm","weight":"165"},{"alt":"童花橙25W 三段调色 直径45cm","id":"44efcf56341b","imgOtherAttr":{},"linkOtherAttr":{},"src":"//gfs17.gomein.net.cn/T1l5djBjDv1RCvBVdK","title":"童花橙25W 三段调色 直径45cm","weight":"166"},{"alt":"棱影25W 三段调色 直径39cm","id":"ad80d3b67a0c","imgOtherAttr":{},"linkOtherAttr":{},"src":"//gfs17.gomein.net.cn/T1X_J_BXYv1RCvBVdK","title":"棱影25W 三段调色 直径39cm","weight":"184"}]}],"sapSkuType":"ZBBC","selltype":"0","shelfCtgy":"PR01","shopFlag":"1","shopName":"FSL佛山照明官方旗舰店","shopNo":"80009222","sku":"pop8010875178","skuBlackList":false,"skuId":"pop8010875178","skuNo":"8010875178","skuNoMap":{"pop8010549942":"8010549942","pop8010875165":"8010875165","pop8010875166":"8010875166","pop8010875167":"8010875167","pop8010875168":"8010875168","pop8010875169":"8010875169","pop8010875170":"8010875170","pop8010875171":"8010875171","pop8010875172":"8010875172","pop8010875173":"8010875173","pop8010875174":"8010875174","pop8010875175":"8010875175","pop8010875176":"8010875176","pop8010875177":"8010875177","pop8010875178":"8010875178","pop8010875179":"8010875179","pop8010875180":"8010875180","pop8010875181":"8010875181","pop8010875182":"8010875182","pop8010875183":"8010875183"},"skuType":"ZBBC","stats":1,"suitSku":[],"threeDflag":false,"vipShopFlag":"0"},{"affixAttr":{"15头 带光源 A款灯罩":"pop8009602200","32头 带光源定制款":"pop8009602203","6头 带光源 A款灯罩":"pop8009602202","8头 带光源 A款灯罩":"pop8009602201","pagType":"1","skuId":"pop8009602202"},"brand":"汉斯威诺","brandCode":"34396","brandId":"242608335","buyWay":[],"bztType":1,"description":"汉斯威诺水晶吊灯","detailHref":"//item.gome.com.cn/A0006128922-pop8009602202.html","energyState":0,"gomePrice":899,"goodsColor":[],"goodsImgs":[{"href":"//item.gome.com.cn/bigimage/A0006128922-pop8009602202.html","imgOtherAttr":{},"linkOtherAttr":{},"src":"//gfs17.gomein.net.cn/T1biATB5_v1RCvBVdK"},{"href":"//item.gome.com.cn/bigimage/A0006128922-pop8009602202.html","imgOtherAttr":{},"linkOtherAttr":{},"src":"//gfs2.gomein.net.cn/T101hTBKLT1RCvBVdK"},{"href":"//item.gome.com.cn/bigimage/A0006128922-pop8009602202.html","imgOtherAttr":{},"linkOtherAttr":{},"src":"//gfs2.gomein.net.cn/T1Y1hTBvhT1RCvBVdK"},{"href":"//item.gome.com.cn/bigimage/A0006128922-pop8009602202.html","imgOtherAttr":{},"linkOtherAttr":{},"src":"//gfs3.gomein.net.cn/T1iuVTBKVv1RCvBVdK"},{"href":"//item.gome.com.cn/bigimage/A0006128922-pop8009602202.html","imgOtherAttr":{},"linkOtherAttr":{},"src":"//gfs3.gomein.net.cn/T1buWTBQxT1RCvBVdK"}],"htmlHref":"//desc.gome.com.cn/html/bbchtml/productDesc/descHtml201612/desc04/A0006128922.html","name":"汉斯威诺水晶吊灯","operADHref":"//desc.gome.com.cn/advert/platformad/cat21445661/top.html","price":0,"productId":"A0006128922","productType":"product","programId":"111111111","salesProperty":[{"booleanMainsale":"true","booleanPic":"true","chinesename":"颜色","hidden":"false","salesNameNo":"8ac55c9d2cf8","skutions":[{"alt":"32头 带光源定制款","id":"83759861f001","imgOtherAttr":{},"linkOtherAttr":{},"src":"//gfs17.gomein.net.cn/T158JvBCLT1RCvBVdK","title":"32头 带光源定制款","weight":"11"},{"alt":"15头 带光源 A款灯罩","id":"5c791cc1dce4","imgOtherAttr":{},"linkOtherAttr":{},"src":"//gfs17.gomein.net.cn/T1jDxTBXZT1RCvBVdK","title":"15头 带光源 A款灯罩","weight":"11"},{"alt":"8头 带光源 A款灯罩","id":"3292007b218a","imgOtherAttr":{},"linkOtherAttr":{},"src":"//gfs17.gomein.net.cn/T1TDETBvKv1RCvBVdK","title":"8头 带光源 A款灯罩","weight":"11"},{"alt":"6头 带光源 A款灯罩","id":"3bc27b044fd0","imgOtherAttr":{},"linkOtherAttr":{},"src":"//gfs17.gomein.net.cn/T1biATB5_v1RCvBVdK","target":"cur","title":"6头 带光源 A款灯罩","weight":"11"}]}],"sapSkuType":"ZBBC","selltype":"0","shelfCtgy":"PR01","shopFlag":"1","shopName":"汉斯威诺灯饰灯具官方旗舰店","shopNo":"80010710","sku":"pop8009602202","skuBlackList":false,"skuId":"pop8009602202","skuNo":"8009602202","skuNoMap":{"pop8009602200":"8009602200","pop8009602201":"8009602201","pop8009602202":"8009602202","pop8009602203":"8009602203"},"skuType":"ZBBC","stats":1,"suitSku":[],"templateId":"m10007","threeDflag":false,"vipShopFlag":"0"},{"affixAttr":{"FV-RB20VL1 通用吊顶带照明&超薄款厚度115CM":"pop8012999175","pagType":"1","skuId":"pop8012999175"},"brand":"松下(Panasonic)","brandCode":"00008","brandId":"10000017","buyWay":[],"bztType":1,"detailHref":"//item.gome.com.cn/A0006608484-pop8012999175.html","energyState":0,"gomePrice":2299,"goodsColor":[],"goodsImgs":[{"href":"//item.gome.com.cn/bigimage/A0006608484-pop8012999175.html","imgOtherAttr":{},"linkOtherAttr":{},"src":"//gfs17.gomein.net.cn/T1YyEyB7AT1RCvBVdK"},{"href":"//item.gome.com.cn/bigimage/A0006608484-pop8012999175.html","imgOtherAttr":{},"linkOtherAttr":{},"src":"//gfs4.gomein.net.cn/T1FWVXBjWT1RCvBVdK"},{"href":"//item.gome.com.cn/bigimage/A0006608484-pop8012999175.html","imgOtherAttr":{},"linkOtherAttr":{},"src":"//gfs4.gomein.net.cn/T1lWKXBC_v1RCvBVdK"},{"href":"//item.gome.com.cn/bigimage/A0006608484-pop8012999175.html","imgOtherAttr":{},"linkOtherAttr":{},"src":"//gfs1.gomein.net.cn/T1maEyBmdT1RCvBVdK"},{"href":"//item.gome.com.cn/bigimage/A0006608484-pop8012999175.html","imgOtherAttr":{},"linkOtherAttr":{},"src":"//gfs3.gomein.net.cn/T1abKXBCLv1RCvBVdK"}],"htmlHref":"//desc.gome.com.cn/html/bbchtml/productDesc/descHtml201909/desc04/A0006608484.html","name":"松下（Panasonic）新款风暖浴霸多功能暖风机风暖机2100w卫生间浴室带照明 支持APP控制(01 默认)","operADHref":"//desc.gome.com.cn/advert/platformad/cat21445683/top.html","price":0,"productId":"A0006608484","productType":"product","programId":"111111111","salesProperty":[{"booleanMainsale":"true","booleanPic":"true","chinesename":"颜色","hidden":"false","salesNameNo":"8ac55c9d2cf8","skutions":[{"alt":"FV-RB20VL1 通用吊顶带照明","id":"4ab6294cb875","imgOtherAttr":{},"linkOtherAttr":{},"src":"//gfs17.gomein.net.cn/T1YyEyB7AT1RCvBVdK","target":"cur","title":"FV-RB20VL1 （通用吊顶带照明）","weight":"0"}]},{"booleanMainsale":"false","booleanPic":"false","chinesename":"版本","hidden":"false","salesNameNo":"c80c62c4448d","skutions":[{"alt":"超薄款厚度115CM","id":"4decc49ef4cd","imgOtherAttr":{},"linkOtherAttr":{},"target":"cur","title":"超薄款厚度11.5CM","weight":"0"}]}],"sapSkuType":"ZBBC","selltype":"0","shelfCtgy":"PR01","shopFlag":"1","shopName":"松下智慧家居旗舰店","shopNo":"80017133","sku":"pop8012999175","skuBlackList":false,"skuId":"pop8012999175","skuNo":"8012999175","skuNoMap":{"pop8012999175":"8012999175"},"skuType":"ZBBC","stats":1,"suitSku":[],"threeDflag":false,"vipShopFlag":"0"},{"affixAttr":{"10A三孔":"pop8010206508","10A三孔带开":"pop8010206509","10A四孔":"pop8010206510","16A三孔":"pop8010206506","16A三孔带开":"pop8010206507","2位音响":"pop8010206511","4位音响":"pop8010206853","pagType":"1","skuId":"pop8010200244","一开单控五孔":"pop8010200245","三开单控":"pop8010206866","三开单控LED":"pop8010206858","三开双控":"pop8010206867","三开双控LED":"pop8010206859","三连边框":"pop8010207531","中途开关":"pop8010207518","二连边框":"pop8010207530","五孔":"pop8010200244","五孔带USB":"pop8010206504","五连边框":"pop8010207533","出门开关":"pop8010207519","单开单控":"pop8010206862","单开单控LED":"pop8010206854","单开双控":"pop8010206863","单开双控LED":"pop8010206855","双USB插座":"pop8010206505","双开单控":"pop8010206864","双开单控LED":"pop8010206856","双开双控":"pop8010206865","双开双控LED":"pop8010206857","双电脑插座":"pop8010207527","四开单控":"pop8010206868","四开单控LED":"pop8010206860","四开双控":"pop8010206869","四开双控LED":"pop8010206861","四连边框":"pop8010207532","宽频电视插座":"pop8010207524","报警开关":"pop8010207521","电脑插座":"pop8010207522","电视插座":"pop8010207523","电视电脑":"pop8010207528","电话插座":"pop8010207525","电话电脑插座":"pop8010207526","空白面板":"pop8010207529","门铃开关":"pop8010207520"},"brand":"西门子(siemens)","brandCode":"00025","brandId":"10000031","buyWay":[],"bztType":1,"detailHref":"//item.gome.com.cn/A0006265915-pop8010200244.html","energyState":0,"gomePrice":43.8,"goodsColor":[],"goodsImgs":[{"href":"//item.gome.com.cn/bigimage/A0006265915-pop8010200244.html","imgOtherAttr":{},"linkOtherAttr":{},"src":"//gfs17.gomein.net.cn/T1A6hvBjxj1RCvBVdK"},{"href":"//item.gome.com.cn/bigimage/A0006265915-pop8010200244.html","imgOtherAttr":{},"linkOtherAttr":{},"src":"//gfs2.gomein.net.cn/T1vchvBjKg1RCvBVdK"},{"href":"//item.gome.com.cn/bigimage/A0006265915-pop8010200244.html","imgOtherAttr":{},"linkOtherAttr":{},"src":"//gfs4.gomein.net.cn/T1l6EvBKDQ1RCvBVdK"},{"href":"//item.gome.com.cn/bigimage/A0006265915-pop8010200244.html","imgOtherAttr":{},"linkOtherAttr":{},"src":"//gfs2.gomein.net.cn/T1echvBQbj1RCvBVdK"},{"href":"//item.gome.com.cn/bigimage/A0006265915-pop8010200244.html","imgOtherAttr":{},"linkOtherAttr":{},"src":"//gfs.gomein.net.cn/T1_QJsBmKT1RCvBVdK"}],"htmlHref":"//desc.gome.com.cn/html/bbchtml/productDesc/descHtml201707/desc04/A0006265915.html","name":"西门子五孔插座睿致系列","operADHref":"//desc.gome.com.cn/advert/platformad/cat21445671/top.html","price":0,"productId":"A0006265915","productType":"product","programId":"111111111","salesProperty":[{"booleanMainsale":"true","booleanPic":"false","chinesename":"版本","hidden":"false","salesNameNo":"c80c62c4448d","skutions":[{"alt":"五孔","id":"826900a8c66d","imgOtherAttr":{},"linkOtherAttr":{},"target":"cur","title":"五孔","weight":"1"},{"alt":"一开单控五孔","id":"e7919574dd72","imgOtherAttr":{},"linkOtherAttr":{},"title":"一开单控五孔","weight":"2"},{"alt":"五孔带USB","id":"9a0c8e14ae00","imgOtherAttr":{},"linkOtherAttr":{},"title":"五孔带USB","weight":"3"},{"alt":"双USB插座","id":"e9638f6a2541","imgOtherAttr":{},"linkOtherAttr":{},"title":"双USB插座","weight":"5"},{"alt":"16A三孔","id":"8d15aa9b9b2b","imgOtherAttr":{},"linkOtherAttr":{},"title":"16A三孔","weight":"6"},{"alt":"16A三孔带开","id":"5f51d4a808f6","imgOtherAttr":{},"linkOtherAttr":{},"title":"16A三孔带开","weight":"7"},{"alt":"10A三孔","id":"1f960616e0c2","imgOtherAttr":{},"linkOtherAttr":{},"title":"10A三孔","weight":"8"},{"alt":"10A三孔带开","id":"6503967c7354","imgOtherAttr":{},"linkOtherAttr":{},"title":"10A三孔带开","weight":"9"},{"alt":"10A四孔","id":"1499b396e5bf","imgOtherAttr":{},"linkOtherAttr":{},"title":"10A四孔","weight":"10"},{"alt":"2位音响","id":"d9397b388e71","imgOtherAttr":{},"linkOtherAttr":{},"title":"2位音响","weight":"11"},{"alt":"4位音响","id":"df1b3617fb53","imgOtherAttr":{},"linkOtherAttr":{},"title":"4位音响","weight":"12"},{"alt":"单开单控LED","id":"2b9ff6871ddc","imgOtherAttr":{},"linkOtherAttr":{},"title":"单开单控LED","weight":"13"},{"alt":"单开双控LED","id":"6cc1d5c4838d","imgOtherAttr":{},"linkOtherAttr":{},"title":"单开双控LED","weight":"14"},{"alt":"双开单控LED","id":"f4368d670572","imgOtherAttr":{},"linkOtherAttr":{},"title":"双开单控LED","weight":"15"},{"alt":"双开双控LED","id":"0a40caf493c5","imgOtherAttr":{},"linkOtherAttr":{},"title":"双开双控LED","weight":"16"},{"alt":"三开单控LED","id":"8cab792ac324","imgOtherAttr":{},"linkOtherAttr":{},"title":"三开单控LED","weight":"17"},{"alt":"三开双控LED","id":"b5e2b35c20c5","imgOtherAttr":{},"linkOtherAttr":{},"title":"三开双控LED","weight":"18"},{"alt":"四开单控LED","id":"5ab3430cd8b6","imgOtherAttr":{},"linkOtherAttr":{},"title":"四开单控LED","weight":"19"},{"alt":"四开双控LED","id":"690a79f4ce17","imgOtherAttr":{},"linkOtherAttr":{},"title":"四开双控LED","weight":"20"},{"alt":"单开单控","id":"79426042defe","imgOtherAttr":{},"linkOtherAttr":{},"title":"单开单控","weight":"21"},{"alt":"单开双控","id":"a5dfe469cc37","imgOtherAttr":{},"linkOtherAttr":{},"title":"单开双控","weight":"22"},{"alt":"双开单控","id":"a85b06fa0c5c","imgOtherAttr":{},"linkOtherAttr":{},"title":"双开单控","weight":"23"},{"alt":"双开双控","id":"29ca03cad021","imgOtherAttr":{},"linkOtherAttr":{},"title":"双开双控","weight":"24"},{"alt":"三开单控","id":"60d7bcbc22d9","imgOtherAttr":{},"linkOtherAttr":{},"title":"三开单控","weight":"25"},{"alt":"三开双控","id":"c941ead8c7d2","imgOtherAttr":{},"linkOtherAttr":{},"title":"三开双控","weight":"26"},{"alt":"四开单控","id":"66768c8b2923","imgOtherAttr":{},"linkOtherAttr":{},"title":"四开单控","weight":"27"},{"alt":"四开双控","id":"006300f20c7d","imgOtherAttr":{},"linkOtherAttr":{},"title":"四开双控","weight":"28"},{"alt":"中途开关","id":"91a86a06732b","imgOtherAttr":{},"linkOtherAttr":{},"title":"中途开关","weight":"29"},{"alt":"出门开关","id":"b99d9d13e4e6","imgOtherAttr":{},"linkOtherAttr":{},"title":"出门开关","weight":"30"},{"alt":"门铃开关","id":"6808c1290a10","imgOtherAttr":{},"linkOtherAttr":{},"title":"门铃开关","weight":"31"},{"alt":"报警开关","id":"19defb8d9138","imgOtherAttr":{},"linkOtherAttr":{},"title":"报警开关","weight":"32"},{"alt":"电脑插座","id":"1942d12bf2c2","imgOtherAttr":{},"linkOtherAttr":{},"title":"电脑插座","weight":"33"},{"alt":"电视插座","id":"c7fb0a59d583","imgOtherAttr":{},"linkOtherAttr":{},"title":"电视插座","weight":"34"},{"alt":"宽频电视插座","id":"947a2bf54aa6","imgOtherAttr":{},"linkOtherAttr":{},"title":"宽频电视插座","weight":"35"},{"alt":"电话插座","id":"34c79a1c5393","imgOtherAttr":{},"linkOtherAttr":{},"title":"电话插座","weight":"36"},{"alt":"电话电脑插座","id":"6e355aaa8c8a","imgOtherAttr":{},"linkOtherAttr":{},"title":"电话电脑插座","weight":"37"},{"alt":"双电脑插座","id":"44d524235e4a","imgOtherAttr":{},"linkOtherAttr":{},"title":"双电脑插座","weight":"38"},{"alt":"电视电脑","id":"491a923abe23","imgOtherAttr":{},"linkOtherAttr":{},"title":"电视电脑","weight":"39"},{"alt":"空白面板","id":"a567c91b2853","imgOtherAttr":{},"linkOtherAttr":{},"title":"空白面板","weight":"40"},{"alt":"二连边框","id":"917fe8516e4f","imgOtherAttr":{},"linkOtherAttr":{},"title":"二连边框","weight":"41"},{"alt":"三连边框","id":"bbefc1090893","imgOtherAttr":{},"linkOtherAttr":{},"title":"三连边框","weight":"42"},{"alt":"四连边框","id":"0b7fd3abeb18","imgOtherAttr":{},"linkOtherAttr":{},"title":"四连边框","weight":"43"},{"alt":"五连边框","id":"bde2040eaa4d","imgOtherAttr":{},"linkOtherAttr":{},"title":"五连边框","weight":"44"}]}],"sapSkuType":"ZBBC","selltype":"0","shelfCtgy":"PR01","shopFlag":"1","shopName":"西门子天域专营店","shopNo":"80001644","sku":"pop8010200244","skuBlackList":false,"skuId":"pop8010200244","skuNo":"8010200244","skuNoMap":{"pop8010200244":"8010200244","pop8010200245":"8010200245","pop8010206504":"8010206504","pop8010206505":"8010206505","pop8010206506":"8010206506","pop8010206507":"8010206507","pop8010206508":"8010206508","pop8010206509":"8010206509","pop8010206510":"8010206510","pop8010206511":"8010206511","pop8010206853":"8010206853","pop8010206854":"8010206854","pop8010206855":"8010206855","pop8010206856":"8010206856","pop8010206857":"8010206857","pop8010206858":"8010206858","pop8010206859":"8010206859","pop8010206860":"8010206860","pop8010206861":"8010206861","pop8010206862":"8010206862","pop8010206863":"8010206863","pop8010206864":"8010206864","pop8010206865":"8010206865","pop8010206866":"8010206866","pop8010206867":"8010206867","pop8010206868":"8010206868","pop8010206869":"8010206869","pop8010207518":"8010207518","pop8010207519":"8010207519","pop8010207520":"8010207520","pop8010207521":"8010207521","pop8010207522":"8010207522","pop8010207523":"8010207523","pop8010207524":"8010207524","pop8010207525":"8010207525","pop8010207526":"8010207526","pop8010207527":"8010207527","pop8010207528":"8010207528","pop8010207529":"8010207529","pop8010207530":"8010207530","pop8010207531":"8010207531","pop8010207532":"8010207532","pop8010207533":"8010207533"},"skuType":"ZBBC","stats":1,"suitSku":[],"threeDflag":false,"vipShopFlag":"0"},{"affixAttr":{"pagType":"1","skuId":"pop8013053940","默认":"pop8013053940"},"brand":"Aqara","brandCode":"44702","brandId":"300008764","buyWay":[],"bztType":1,"detailHref":"//item.gome.com.cn/A0006619422-pop8013053940.html","energyState":0,"gomePrice":1299,"goodsColor":[],"goodsImgs":[{"href":"//item.gome.com.cn/bigimage/A0006619422-pop8013053940.html","imgOtherAttr":{},"linkOtherAttr":{},"src":"//gfs17.gomein.net.cn/T1C9hyBTYv1RCvBVdK"},{"href":"//item.gome.com.cn/bigimage/A0006619422-pop8013053940.html","imgOtherAttr":{},"linkOtherAttr":{},"src":"//gfs2.gomein.net.cn/T1ygDyBXCv1RCvBVdK"},{"href":"//item.gome.com.cn/bigimage/A0006619422-pop8013053940.html","imgOtherAttr":{},"linkOtherAttr":{},"src":"//gfs4.gomein.net.cn/T1unKyB_xT1RCvBVdK"},{"href":"//item.gome.com.cn/bigimage/A0006619422-pop8013053940.html","imgOtherAttr":{},"linkOtherAttr":{},"src":"//gfs.gomein.net.cn/T1m9byBC_T1RCvBVdK"},{"href":"//item.gome.com.cn/bigimage/A0006619422-pop8013053940.html","imgOtherAttr":{},"linkOtherAttr":{},"src":"//gfs.gomein.net.cn/T1J9VyB4dT1RCvBVdK"}],"htmlHref":"//desc.gome.com.cn/html/bbchtml/productDesc/descHtml201911/desc04/A0006619422.html","name":"Aqara智能门锁N100","operADHref":"//desc.gome.com.cn/advert/platformad/cat21445783/top.html","price":0,"productId":"A0006619422","productType":"product","programId":"111111111","salesProperty":[{"booleanMainsale":"true","booleanPic":"true","chinesename":"颜色","hidden":"false","salesNameNo":"8ac55c9d2cf8","skutions":[{"alt":"默认","id":"cf7c38f1f7fc","imgOtherAttr":{},"linkOtherAttr":{},"src":"//gfs17.gomein.net.cn/T1C9hyBTYv1RCvBVdK","target":"cur","title":"默认","weight":"1"}]}],"sapSkuType":"ZBBC","selltype":"0","shelfCtgy":"PR01","shopFlag":"1","shopName":"Aqara官方旗舰店","shopNo":"80014603","sku":"pop8013053940","skuBlackList":false,"skuId":"pop8013053940","skuNo":"8013053940","skuNoMap":{"pop8013053940":"8013053940"},"skuType":"ZBBC","stats":1,"suitSku":[],"threeDflag":false,"vipShopFlag":"0"},{"affixAttr":{"6950cm方型WIFI右温控":"pop8012945344","6950cm方型WIFI左温控":"pop8012945345","700500S型wifi温控右":"pop8012359018","700500S型wifi温控左":"pop8012359019","pagType":"1","skuId":"pop8012945345"},"brand":"艾芬达(AVONFLOW)","brandCode":"51070","brandId":"300027162","buyWay":[],"bztType":1,"detailHref":"//item.gome.com.cn/A0006505537-pop8012945345.html","energyState":0,"gomePrice":998,"goodsColor":[],"goodsImgs":[{"href":"//item.gome.com.cn/bigimage/A0006505537-pop8012945345.html","imgOtherAttr":{},"linkOtherAttr":{},"src":"//gfs17.gomein.net.cn/T1Ui_yBm_T1RCvBVdK"},{"href":"//item.gome.com.cn/bigimage/A0006505537-pop8012945345.html","imgOtherAttr":{},"linkOtherAttr":{},"src":"//gfs3.gomein.net.cn/T1AuKyBvxT1RCvBVdK"},{"href":"//item.gome.com.cn/bigimage/A0006505537-pop8012945345.html","imgOtherAttr":{},"linkOtherAttr":{},"src":"//gfs3.gomein.net.cn/T1Hf_yBCWT1RCvBVdK"},{"href":"//item.gome.com.cn/bigimage/A0006505537-pop8012945345.html","imgOtherAttr":{},"linkOtherAttr":{},"src":"//gfs2.gomein.net.cn/T1fuZyBTWv1RCvBVdK"},{"href":"//item.gome.com.cn/bigimage/A0006505537-pop8012945345.html","imgOtherAttr":{},"linkOtherAttr":{},"src":"//gfs.gomein.net.cn/T1ELLyB7DT1RCvBVdK"}],"htmlHref":"//desc.gome.com.cn/html/bbchtml/productDesc/descHtml201810/desc04/A0006505537.html","name":"艾芬达 电加热毛巾烘干架","operADHref":"//desc.gome.com.cn/advert/platformad/cat21445655/top.html","price":0,"productId":"A0006505537","productType":"product","programId":"111111111","salesProperty":[{"booleanMainsale":"true","booleanPic":"false","chinesename":"版本","hidden":"false","salesNameNo":"c80c62c4448d","skutions":[{"alt":"6950cm方型WIFI右温控","id":"c147cfec00ea","imgOtherAttr":{},"linkOtherAttr":{},"title":"69*50cm方型WIFI右温控","weight":"1"},{"alt":"6950cm方型WIFI左温控","id":"5768a124ffc2","imgOtherAttr":{},"linkOtherAttr":{},"target":"cur","title":"69*50cm方型WIFI左温控","weight":"1"},{"alt":"700500S型wifi温控右","id":"6a1ec91fad38","imgOtherAttr":{},"linkOtherAttr":{},"title":"700*500（S型wifi温控右）","weight":"3"},{"alt":"700500S型wifi温控左","id":"12ee44e970c4","imgOtherAttr":{},"linkOtherAttr":{},"title":"700*500（S型wifi温控左）","weight":"4"}]}],"sapSkuType":"ZBBC","selltype":"0","shelfCtgy":"PR01","shopFlag":"1","shopName":"艾芬达旗舰店","shopNo":"80016238","sku":"pop8012945345","skuBlackList":false,"skuId":"pop8012945345","skuNo":"8012945345","skuNoMap":{"pop8012359018":"8012359018","pop8012359019":"8012359019","pop8012945344":"8012945344","pop8012945345":"8012945345"},"skuType":"ZBBC","stats":1,"suitSku":[],"threeDflag":false,"vipShopFlag":"0"},{"affixAttr":{"913A遥控负离子浴霸":"pop8012891200","pagType":"1","skuId":"pop8012891200"},"brand":"华帝(vatti)","brandCode":"00092","brandId":"10000581","buyWay":[],"bztType":1,"detailHref":"//item.gome.com.cn/A0006584462-pop8012891200.html","energyState":0,"gomePrice":399,"goodsColor":[],"goodsImgs":[{"href":"//item.gome.com.cn/bigimage/A0006584462-pop8012891200.html","imgOtherAttr":{},"linkOtherAttr":{},"src":"//gfs17.gomein.net.cn/T1SCCXBshT1RCvBVdK"},{"href":"//item.gome.com.cn/bigimage/A0006584462-pop8012891200.html","imgOtherAttr":{},"linkOtherAttr":{},"src":"//gfs3.gomein.net.cn/T1jWdsB4CT1RCvBVdK"},{"href":"//item.gome.com.cn/bigimage/A0006584462-pop8012891200.html","imgOtherAttr":{},"linkOtherAttr":{},"src":"//gfs3.gomein.net.cn/T1DWJsB_Av1RCvBVdK"},{"href":"//item.gome.com.cn/bigimage/A0006584462-pop8012891200.html","imgOtherAttr":{},"linkOtherAttr":{},"src":"//gfs3.gomein.net.cn/T1FxxsBXDv1RCvBVdK"},{"href":"//item.gome.com.cn/bigimage/A0006584462-pop8012891200.html","imgOtherAttr":{},"linkOtherAttr":{},"src":"//gfs1.gomein.net.cn/T1SxZsBCLT1RCvBVdK"}],"htmlHref":"//desc.gome.com.cn/html/bbchtml/productDesc/descHtml201907/desc04/A0006584462.html","name":"华帝 多功能智能风暖浴霸","operADHref":"//desc.gome.com.cn/advert/platformad/cat21445683/top.html","price":0,"productId":"A0006584462","productType":"product","programId":"111111111","salesProperty":[{"booleanMainsale":"true","booleanPic":"true","chinesename":"颜色","hidden":"false","salesNameNo":"8ac55c9d2cf8","skutions":[{"alt":"913A遥控负离子浴霸","id":"bddba8e9dd2b","imgOtherAttr":{},"linkOtherAttr":{},"src":"//gfs17.gomein.net.cn/T1SCCXBshT1RCvBVdK","target":"cur","title":"913A遥控负离子浴霸","weight":"0"}]}],"sapSkuType":"ZBBC","selltype":"0","shelfCtgy":"PR01","shopFlag":"1","shopName":"华帝浴霸旗舰店","shopNo":"80006422","sku":"pop8012891200","skuBlackList":false,"skuId":"pop8012891200","skuNo":"8012891200","skuNoMap":{"pop8012891200":"8012891200"},"skuType":"ZBBC","stats":1,"suitSku":[],"threeDflag":false,"vipShopFlag":"0"}]